odoo/addons/website_sale_tax_toggle/README.rst
odoo/addons/website_sale_tax_toggle/__init__.py
odoo/addons/website_sale_tax_toggle/__manifest__.py
odoo/addons/website_sale_tax_toggle/controllers/__init__.py
odoo/addons/website_sale_tax_toggle/controllers/main.py
odoo/addons/website_sale_tax_toggle/demo/assets.xml
odoo/addons/website_sale_tax_toggle/i18n/ca.po
odoo/addons/website_sale_tax_toggle/i18n/es.po
odoo/addons/website_sale_tax_toggle/i18n/fr.po
odoo/addons/website_sale_tax_toggle/i18n/it.po
odoo/addons/website_sale_tax_toggle/i18n/nl.po
odoo/addons/website_sale_tax_toggle/i18n/pt.po
odoo/addons/website_sale_tax_toggle/i18n/website_sale_tax_toggle.pot
odoo/addons/website_sale_tax_toggle/models/__init__.py
odoo/addons/website_sale_tax_toggle/models/res_users.py
odoo/addons/website_sale_tax_toggle/readme/CONTRIBUTORS.rst
odoo/addons/website_sale_tax_toggle/readme/DESCRIPTION.rst
odoo/addons/website_sale_tax_toggle/readme/USAGE.rst
odoo/addons/website_sale_tax_toggle/static/description/icon.png
odoo/addons/website_sale_tax_toggle/static/description/index.html
odoo/addons/website_sale_tax_toggle/static/src/js/website_sale_tax_toggle.js
odoo/addons/website_sale_tax_toggle/static/src/js/website_sale_tax_toggle_tour.js
odoo/addons/website_sale_tax_toggle/static/src/scss/website_sale_tax_toggle.scss
odoo/addons/website_sale_tax_toggle/tests/__init__.py
odoo/addons/website_sale_tax_toggle/tests/test_website_sale_tax_toggle.py
odoo/addons/website_sale_tax_toggle/views/assets.xml
odoo/addons/website_sale_tax_toggle/views/templates.xml
odoo14_addon_website_sale_tax_toggle-14.0.1.0.1.dev10.dist-info/METADATA
odoo14_addon_website_sale_tax_toggle-14.0.1.0.1.dev10.dist-info/WHEEL
odoo14_addon_website_sale_tax_toggle-14.0.1.0.1.dev10.dist-info/top_level.txt
odoo14_addon_website_sale_tax_toggle-14.0.1.0.1.dev10.dist-info/RECORD
